warp.py
warp_py-0.1.4.dist-info/LICENSE
warp_py-0.1.4.dist-info/METADATA
warp_py-0.1.4.dist-info/WHEEL
warp_py-0.1.4.dist-info/entry_points.txt
warp_py-0.1.4.dist-info/top_level.txt
warp_py-0.1.4.dist-info/RECORD
