Metadata-Version: 2.1
Name: warp-py
Version: 0.1.4
Summary: Warp! - Your lazy ssh command line helper
Home-page: https://gitlab.com/adithya3494/warp
Author: addy3494
Author-email: adithya3494@gmail.com
License: MIT
Platform: UNKNOWN
Classifier: Development Status :: 4 - Beta
Classifier: Environment :: Console
Classifier: Intended Audience :: Developers
Classifier: Intended Audience :: Information Technology
Classifier: Intended Audience :: System Administrators
Classifier: License :: OSI Approved :: MIT License
Classifier: Operating System :: POSIX
Classifier: Programming Language :: Python
Classifier: Topic :: Terminals
License-File: LICENSE
Requires-Dist: iterfzf (==0.5.0.20.0)
